README.txt
setup.py
LibWiser/CodeGeneratorVisitor.py
LibWiser/EasyGo.py
LibWiser/Enums.py
LibWiser/Errors.py
LibWiser/Exceptions.py
LibWiser/FermiSource.py
LibWiser/Foundation.py
LibWiser/Importer.py
LibWiser/Investigation.py
LibWiser/Investigators.py
LibWiser/Main.py
LibWiser/Noise.py
LibWiser/Optics.py
LibWiser/Paths.py
LibWiser/ProgressBar.py
LibWiser/Rayman.py
LibWiser/Scrubs.py
LibWiser/Shortcuts.py
LibWiser/ToolLib.py
LibWiser/ToolLibHigh.py
LibWiser/Types.py
LibWiser/Units.py
LibWiser/Units_old.py
LibWiser/WiserImport.py
LibWiser/__Fundation.py
LibWiser/__init__.py
LibWiser/must.py
LibWiser/version.py
LibWiser.egg-info/PKG-INFO
LibWiser.egg-info/SOURCES.txt
LibWiser.egg-info/dependency_links.txt
LibWiser.egg-info/not-zip-safe
LibWiser.egg-info/requires.txt
LibWiser.egg-info/top_level.txt