Metadata-Version: 2.1
Name: LibWiser
Version: 0.12.15
Summary: Wiser kernel library
Home-page: https://github.com/oasys-elettra-kit/WISEr
Author: Michele Manfredda, Lorenzo Raimondi, Aljosa Hafner
Author-email: michele.manfredda@elettra.eu, lorenzo.raimondi@elettra.eu
Maintainer: Michele Manfredda
Maintainer-email: michele.manfredda@elettra.eu
License: GPLv3
Download-URL: https://github.com/oasys-elettra-kit/WISEr
Keywords: wavefront propagation,simulation
Platform: UNKNOWN
Classifier: Development Status :: 4 - Beta
Classifier: Environment :: Console
Classifier: Environment :: Plugins
Classifier: Programming Language :: Python :: 3
Classifier: Topic :: Software Development :: Libraries :: Python Modules
Classifier: Intended Audience :: Education
Classifier: Intended Audience :: Science/Research
Classifier: Intended Audience :: Developers
